lark_helper/__init__.py
lark_helper/exception.py
lark_helper/token_manager.py
lark_helper/constants/__init__.py
lark_helper/constants/doc.py
lark_helper/constants/file.py
lark_helper/constants/message.py
lark_helper/models/__init__.py
lark_helper/models/bitable.py
lark_helper/models/doc.py
lark_helper/models/file.py
lark_helper/models/message.py
lark_helper/utils/__init__.py
lark_helper/utils/async_request.py
lark_helper/utils/decorator.py
lark_helper/utils/dependency_check.py
lark_helper/utils/log.py
lark_helper/utils/request.py
lark_helper/v1/__init__.py
lark_helper/v1/application.py
lark_helper/v1/bitable.py
lark_helper/v1/chat.py
lark_helper/v1/doc.py
lark_helper/v1/file.py
lark_helper/v1/interactive.py
lark_helper/v1/message.py
lark_helper/v1/user.py
lark_helper/v1/wiki.py
lark_helper/v1_async/__init__.py
lark_helper/v1_async/application.py
lark_helper/v1_async/bitable.py
lark_helper/v1_async/doc.py
lark_helper/v1_async/file.py
lark_helper/v1_async/message.py
lark_helper/v1_async/user.py
lark_helper-0.1.0.dev17.dist-info/METADATA
lark_helper-0.1.0.dev17.dist-info/WHEEL
lark_helper-0.1.0.dev17.dist-info/top_level.txt
lark_helper-0.1.0.dev17.dist-info/RECORD
