Metadata-Version: 2.4
Name: lark-helper
Version: 0.1.0.dev17
Summary: A Python library for interacting with Lark APIs, providing both synchronous and asynchronous interfaces
Author-email: philo-veritas <edison.gee.lan@gmail.com>
Maintainer-email: philo-veritas <edison.gee.lan@gmail.com>
License: MIT
Project-URL: Homepage, https://github.com/philo-veritas/lark-helper
Keywords: lark,api,feishu,bytedance,collaboration,bitable,messaging,async,sync,enterprise,communication
Classifier: Development Status :: 3 - Alpha
Classifier: Intended Audience :: Developers
Classifier: License :: OSI Approved :: MIT License
Classifier: Operating System :: OS Independent
Classifier: Programming Language :: Python :: 3
Classifier: Programming Language :: Python :: 3.10
Classifier: Programming Language :: Python :: 3.11
Classifier: Programming Language :: Python :: 3.12
Classifier: Programming Language :: Python :: 3.13
Classifier: Topic :: Software Development :: Libraries :: Python Modules
Classifier: Topic :: Communications
Classifier: Topic :: Office/Business
Classifier: Topic :: Internet :: WWW/HTTP :: Dynamic Content
Classifier: Topic :: Software Development :: Libraries
Classifier: Framework :: AsyncIO
Classifier: Typing :: Typed
Requires-Python: >=3.12
Requires-Dist: aiohttp>=3.12.14
Requires-Dist: lark-oapi>=1.4.19
Requires-Dist: pydantic>=2.11.7
Requires-Dist: requests>=2.32.4
Requires-Dist: requests-toolbelt>=1.0.0
Provides-Extra: dev
Requires-Dist: build>=1.2.2.post1; extra == "dev"
Requires-Dist: click>=8.1.7; extra == "dev"
Requires-Dist: pytest>=8.4.1; extra == "dev"
Requires-Dist: pytest-asyncio>=1.1.0; extra == "dev"
Requires-Dist: pytest-cov>=5.0.0; extra == "dev"
Requires-Dist: ruff>=0.12.3; extra == "dev"
Requires-Dist: twine>=6.1.0; extra == "dev"
Requires-Dist: mypy>=1.9.0; extra == "dev"
Provides-Extra: test
Requires-Dist: pytest>=8.4.1; extra == "test"
Requires-Dist: pytest-asyncio>=1.1.0; extra == "test"
Requires-Dist: pytest-cov>=5.0.0; extra == "test"
Provides-Extra: docs
Requires-Dist: sphinx>=7.3.7; extra == "docs"
Requires-Dist: sphinx-rtd-theme>=2.0.0; extra == "docs"
